chatgpt_cli/__init__.py
chatgpt_cli/chat.py
chatgpt_cli/conversation.py
utils/__init__.py
utils/cmd.py
utils/file.py
utils/io.py
chatgpt_cli_md-0.1.13.dist-info/LICENSE
chatgpt_cli_md-0.1.13.dist-info/METADATA
chatgpt_cli_md-0.1.13.dist-info/WHEEL
chatgpt_cli_md-0.1.13.dist-info/entry_points.txt
chatgpt_cli_md-0.1.13.dist-info/top_level.txt
chatgpt_cli_md-0.1.13.dist-info/RECORD
