Metadata-Version: 2.1
Name: chatgpt-cli-md
Version: 0.1.13
Summary: A markdown-supported command-line interface tool that connects to ChatGPT using OpenAI's API key.
Author-email: Jerry Yang <efjerryyang@outlook.com>
License: MIT License
Project-URL: Homepage, https://github.com/efJerryYang/chatgpt-cli
Project-URL: Bug Tracker, https://github.com/efJerryYang/chatgpt-cli/issues
Project-URL: Repository, https://github.com/efJerryYang/chatgpt-cli.git
Keywords: chatbot,chatgpt,chatgpt-cli,openai,markdown,cli,command-line
Classifier: Programming Language :: Python :: 3
Classifier: License :: OSI Approved :: MIT License
Classifier: Operating System :: OS Independent
Requires-Python: >=3.8
License-File: LICENSE
Requires-Dist: openai (>=0.27.0)
Requires-Dist: pyyaml (>=6.0)
Requires-Dist: rich (>=13.3.1)
Requires-Dist: pyreadline3 (>=3.4.1)
